hyperion/__init__.py
hyperion/client.py
hyperion/const.py
hyperion/py.typed
hyperhdr_py_2-0.7.6.dist-info/LICENSE
hyperhdr_py_2-0.7.6.dist-info/METADATA
hyperhdr_py_2-0.7.6.dist-info/WHEEL
hyperhdr_py_2-0.7.6.dist-info/RECORD
